streamsets/sdk/__init__.py
streamsets/sdk/__version__.py
streamsets/sdk/analytics.py
streamsets/sdk/aster_api.py
streamsets/sdk/constants.py
streamsets/sdk/exceptions.py
streamsets/sdk/models.py
streamsets/sdk/sch.py
streamsets/sdk/sch_api.py
streamsets/sdk/sch_models.py
streamsets/sdk/sdc.py
streamsets/sdk/sdc_api.py
streamsets/sdk/sdc_models.py
streamsets/sdk/st.py
streamsets/sdk/st_api.py
streamsets/sdk/st_models.py
streamsets/sdk/utils.py
streamsets-6.6.2.dist-info/METADATA
streamsets-6.6.2.dist-info/WHEEL
streamsets-6.6.2.dist-info/top_level.txt
streamsets-6.6.2.dist-info/RECORD
